PyBenchFCN/Factory.py
PyBenchFCN/SingleObjectiveProblem.py
PyBenchFCN/Tool.py
PyBenchFCN/__init__.py
PyBenchFCN-1.0.3.dist-info/LICENSE
PyBenchFCN-1.0.3.dist-info/METADATA
PyBenchFCN-1.0.3.dist-info/WHEEL
PyBenchFCN-1.0.3.dist-info/top_level.txt
PyBenchFCN-1.0.3.dist-info/RECORD
