Metadata-Version: 2.1
Name: PyBenchFCN
Version: 1.0.3
Summary: A python implementation of optimization benchmarks
Home-page: https://github.com/Y1fanHE/PyBenchFCN
Author: Yifan He
Author-email: he.yifan.xs@alumni.tsukuba.ac.jp
License: UNKNOWN
Platform: UNKNOWN
Classifier: Programming Language :: Python :: 3
Classifier: License :: OSI Approved :: MIT License
Classifier: Operating System :: OS Independent
Requires-Python: >=3.6
